cfactor/MainWindow.py
cfactor/__init__.py
cfactor/export.py
cfactor/models.py
cfactor-1.5.4.dist-info/METADATA
cfactor-1.5.4.dist-info/WHEEL
cfactor-1.5.4.dist-info/top_level.txt
cfactor-1.5.4.dist-info/RECORD
